glang/__init__.py
glang/driver.py
glang/graphene_parser.py
glang/target.py
glang/codegen/__init__.py
glang/codegen/builtin_callables.py
glang/codegen/builtin_types.py
glang/codegen/debug.py
glang/codegen/expressions.py
glang/codegen/floats.py
glang/codegen/generatable.py
glang/codegen/interfaces.py
glang/codegen/mangling.py
glang/codegen/strings.py
glang/codegen/translation_unit.py
glang/codegen/type_conversions.py
glang/codegen/type_resolution.py
glang/codegen/user_facing_errors.py
glang/lib/std/algorithms.c3
glang/lib/std/arithmetic.c3
glang/lib/std/assert.c3
glang/lib/std/assignments.c3
glang/lib/std/fcntl.c3
glang/lib/std/format.c3
glang/lib/std/io.c3
glang/lib/std/iterators.c3
glang/lib/std/json.c3
glang/lib/std/logical.c3
glang/lib/std/math.c3
glang/lib/std/memory.c3
glang/lib/std/rb_tree.c3
glang/lib/std/span.c3
glang/lib/std/string.c3
glang/lib/std/type_traits.c3
glang/lib/std/unistd.c3
glang/lib/std/util.c3
glang/lib/std/vector.c3
glang/lib/std/wrappers.c3
glang/lib/std/aarch64_linux/runtime.S
glang/lib/std/aarch64_linux/syscalls.c3
glang/lib/std/aarch64_linux/sys/kstat.c3
glang/lib/std/arm_linux/runtime.S
glang/lib/std/arm_linux/syscalls.c3
glang/lib/std/sys/mman.c3
glang/lib/std/sys/stat.c3
glang/lib/std/sys/types.c3
glang/lib/std/sys/uio.c3
glang/lib/std/x86_64_linux/runtime.S
glang/lib/std/x86_64_linux/syscalls.c3
glang/lib/std/x86_64_linux/sys/kstat.c3
glang/parser/__init__.py
glang/parser/file_info.c3
glang/parser/lexer_parser.py
glang/parser/parser.c3
glang/parser/self_hosted_parser.py
glang/parser/syntax_tree.c3
glang/targets/aarch64_linux.yml
glang/targets/arm_linux.yml
glang/targets/x86_64_linux.yml
glang/utils/stack.py
glang/bin/parser
glang-0.4.1.dist-info/METADATA
glang-0.4.1.dist-info/WHEEL
glang-0.4.1.dist-info/entry_points.txt
glang-0.4.1.dist-info/licenses/LICENSE
glang-0.4.1.dist-info/RECORD
