Metadata-Version: 2.3
Name: glang
Version: 0.4.1
Summary: A Graphene front-end for LLVM
Project-URL: Homepage, https://github.com/DaveDuck321/GrapheneLang/
Project-URL: Bug Tracker, https://github.com/DaveDuck321/GrapheneLang/issues
Author-email: Antros Economides <antroseconomides@hotmail.co.uk>, Tom Grant <thomas.grant.mail@gmail.com>
License-Expression: AGPL-3.0-only
License-File: LICENSE
Classifier: Development Status :: 3 - Alpha
Classifier: License :: OSI Approved :: GNU Affero General Public License v3
Classifier: Operating System :: POSIX :: Linux
Classifier: Programming Language :: Python :: 3
Classifier: Topic :: Software Development :: Compilers
Requires-Python: >=3.12
Requires-Dist: pyyaml~=6.0
Requires-Dist: typed-argument-parser~=1.8
